spflow-0.0.48.dist-info/licenses/LICENSE.md
spn/__init__.py
spn/algorithms/CnetStructureLearning.py
spn/algorithms/Condition.py
spn/algorithms/EM.py
spn/algorithms/Gradient.py
spn/algorithms/Inference.py
spn/algorithms/LeafLearning.py
spn/algorithms/LearningWrappers.py
spn/algorithms/MPE.py
spn/algorithms/Marginalization.py
spn/algorithms/Posteriors.py
spn/algorithms/Sampling.py
spn/algorithms/SamplingRange.py
spn/algorithms/Statistics.py
spn/algorithms/StructureLearning.py
spn/algorithms/TransformStructure.py
spn/algorithms/Validity.py
spn/algorithms/__init__.py
spn/algorithms/sklearn.py
spn/algorithms/layerwise/__init__.py
spn/algorithms/layerwise/clipper.py
spn/algorithms/layerwise/distributions.py
spn/algorithms/layerwise/layers.py
spn/algorithms/layerwise/type_checks.py
spn/algorithms/layerwise/utils.py
spn/algorithms/measures/InformationTheory.py
spn/algorithms/measures/WeightOfEvidence.py
spn/algorithms/measures/__init__.py
spn/algorithms/splitting/Base.py
spn/algorithms/splitting/Clustering.py
spn/algorithms/splitting/Conditioning.py
spn/algorithms/splitting/ParametricTests.py
spn/algorithms/splitting/PoissonStabilityTest.py
spn/algorithms/splitting/RDC.py
spn/algorithms/splitting/Random.py
spn/algorithms/splitting/__init__.py
spn/algorithms/splitting/mixedClustering.R
spn/algorithms/splitting/rdc.R
spn/algorithms/stats/Expectations.py
spn/algorithms/stats/Moments.py
spn/algorithms/stats/__init__.py
spn/data/__init__.py
spn/data/datasets.py
spn/experiments/__init__.py
spn/experiments/AQP/Ranges.py
spn/experiments/AQP/__init__.py
spn/experiments/AQP/expectation/Expectations.py
spn/experiments/AQP/expectation/__init__.py
spn/experiments/AQP/leaves/__init__.py
spn/experiments/AQP/leaves/identity/Expectation.py
spn/experiments/AQP/leaves/identity/IdentityNumeric.py
spn/experiments/AQP/leaves/identity/Inference.py
spn/experiments/AQP/leaves/identity/InferenceRange.py
spn/experiments/AQP/leaves/identity/SamplingRange.py
spn/experiments/AQP/leaves/identity/__init__.py
spflow-0.0.48.dist-info/METADATA
spflow-0.0.48.dist-info/WHEEL
spflow-0.0.48.dist-info/top_level.txt
spflow-0.0.48.dist-info/RECORD
