Metadata-Version: 2.4
Name: spflow
Version: 0.0.48
Summary: Sum Product Flow: An Easy and Extensible Library for Sum-Product Networks
Author-email: "Alejandro Molina et al." <molina@cs.tu-darmstadt.de>, Steven Braun <steven.braun@cs.tu-darmstadt.de>
License: Apache-2.0
Project-URL: Homepage, https://github.com/SPFlow/SPFlow
Project-URL: Repository, https://github.com/SPFlow/SPFlow.git
Classifier: Programming Language :: Python :: 3
Classifier: Programming Language :: Python :: 3.10
Classifier: Programming Language :: Python :: 3.11
Classifier: Programming Language :: Python :: 3.12
Classifier: License :: OSI Approved :: Apache Software License
Classifier: Operating System :: OS Independent
Requires-Python: <3.13,>=3.10
License-File: LICENSE.md
Requires-Dist: numpy<2.3.0,>=1.22.4
Requires-Dist: scikit-learn>=1.4.0
Requires-Dist: statsmodels>=0.14.0
Requires-Dist: scipy>=1.10.0
Requires-Dist: networkx>=3.0
Requires-Dist: joblib>=1.0.0
Requires-Dist: matplotlib>=3.6.0
Requires-Dist: pydot>=2.0.0
Requires-Dist: lark-parser>=0.9.0
Requires-Dist: tqdm>=4.1.0
Requires-Dist: ete3>=3.1.1
Requires-Dist: sympy>=1.7.0
Requires-Dist: PyQt5>=5.15.10; sys_platform != "win32"
Requires-Dist: arff>=0.9
Requires-Dist: tensorflow>=2.18.0
Requires-Dist: tensorflow-probability[tf]>=0.24.0
Requires-Dist: torch>=2.3.0
Requires-Dist: torchvision>=0.18
Provides-Extra: r
Requires-Dist: rpy2>=3.5.0; extra == "r"
Provides-Extra: tsne
Provides-Extra: test
Requires-Dist: pytest>=8.4.2; extra == "test"
Requires-Dist: pytest-xdist>=3.8.0; extra == "test"
Provides-Extra: dev
Requires-Dist: build>=1.3.0; extra == "dev"
Requires-Dist: twine>=6.2.0; extra == "dev"
Dynamic: license-file
